flexistack/__init__.py
flexistack/flexistack.py
flexistack/helper.py
flexistack-0.2.33.dist-info/licenses/LICENSE
flexistack-0.2.33.dist-info/METADATA
flexistack-0.2.33.dist-info/WHEEL
flexistack-0.2.33.dist-info/top_level.txt
flexistack-0.2.33.dist-info/RECORD
