Metadata-Version: 2.4
Name: flexistack
Version: 0.2.33
Summary: Simple and easy to use framework
Author-email: "Ioannis D (devcoons)" <support@devcoons.com>
License: MIT License
Project-URL: Homepage, https://github.com/devcoons/flexistack
Project-URL: Issues, https://github.com/devcoons/flexistack/issues
Keywords: flexistack,autoloader
Classifier: Development Status :: 5 - Production/Stable
Classifier: Intended Audience :: Developers
Classifier: Natural Language :: English
Classifier: License :: OSI Approved :: MIT License
Classifier: Operating System :: OS Independent
Classifier: Programming Language :: Python :: 3.8
Classifier: Programming Language :: Python :: 3.9
Classifier: Programming Language :: Python :: 3.10
Classifier: Programming Language :: Python :: 3.11
Classifier: Programming Language :: Python :: 3.12
Classifier: Programming Language :: Python :: Implementation :: PyPy
Requires-Python: >=3.9
License-File: LICENSE
Requires-Dist: psutil>=5.9.8
Requires-Dist: pyaes>=1.6.1
Requires-Dist: argparse>=1.4.0
Requires-Dist: argparse_addons>=0.12.0
Requires-Dist: configvault>=0.0.2
Requires-Dist: consolio>=0.1.11
Requires-Dist: pywin32; os_name == "nt"
Provides-Extra: dev
Requires-Dist: pip-tools; extra == "dev"
Dynamic: license-file
